README.md
setup.py
Kivy5.egg-info/PKG-INFO
Kivy5.egg-info/SOURCES.txt
Kivy5.egg-info/dependency_links.txt
Kivy5.egg-info/requires.txt
Kivy5.egg-info/top_level.txt
kivy4/__init__.py