Metadata-Version: 2.1
Name: Kivy5
Version: 4.0.3
Summary: This package allows you to create Kivy projects faster with a pre-made kivy template.
Home-page: UNKNOWN
Author: Eshqol Development
Author-email: support@eshqol.com
License: MIT
Platform: UNKNOWN
Requires-Python: >=3.7
